rustils/__init__.py
rustils/py_utils.py
rustils-0.1.0.dist-info/LICENSE
rustils-0.1.0.dist-info/METADATA
rustils-0.1.0.dist-info/WHEEL
rustils-0.1.0.dist-info/RECORD
