Metadata-Version: 2.1
Name: rustils
Version: 0.1.0
Summary: A collection of utility functions
License: MIT
Author: tsonglew
Requires-Python: >=3.9
Classifier: License :: OSI Approved :: MIT License
Classifier: Programming Language :: Python :: 3
Classifier: Programming Language :: Python :: 3.9
Classifier: Programming Language :: Python :: 3.10
Classifier: Programming Language :: Python :: 3.11
Classifier: Programming Language :: Python :: 3.12
Classifier: Programming Language :: Python :: 3.13
Requires-Dist: maturin (>=1.4.0,<2.0.0)
